unifi_ap/__init__.py
unifi_ap/unifi_ap.py
unifi_ap-0.0.1.dist-info/LICENSE
unifi_ap-0.0.1.dist-info/METADATA
unifi_ap-0.0.1.dist-info/WHEEL
unifi_ap-0.0.1.dist-info/top_level.txt
unifi_ap-0.0.1.dist-info/RECORD
