Metadata-Version: 2.1
Name: unifi-ap
Version: 0.0.1
Summary: Python API for UniFi accesspoints
Author-email: Tobias Perschon <tobias@perschon.at>
Project-URL: Homepage, https://github.com/tofuSCHNITZEL/unifi_ap
Project-URL: Issues, https://github.com/tofuSCHNITZEL/unifi_ap/issues
Classifier: Programming Language :: Python :: 3
Classifier: License :: OSI Approved :: MIT License
Classifier: Operating System :: OS Independent
Requires-Python: >=3.8
License-File: LICENSE
Requires-Dist: paramiko ==3.3.1
